thonnycontrib/pololu-3pi-2040-robot/__init__.py
thonnycontrib/pololu-zumo-2040-robot/__init__.py
thonny_pololu-1.1.0.dist-info/METADATA
thonny_pololu-1.1.0.dist-info/WHEEL
thonny_pololu-1.1.0.dist-info/licenses/LICENSE.txt
thonny_pololu-1.1.0.dist-info/RECORD
