Metadata-Version: 2.1
Name: thonny-pololu
Version: 1.1.0
Summary: Pololu 3pi+ 2040 Robot and Zumo 2040 Robot support for Thonny.
Project-URL: Homepage, https://github.com/pololu/thonny-pololu
Project-URL: Bug Tracker, https://github.com/pololu/thonny-pololu/issues
Author-email: Paul Grayson <dev-paul@pololu.com>
License-File: LICENSE.txt
Classifier: License :: OSI Approved :: MIT License
Classifier: Operating System :: OS Independent
Classifier: Programming Language :: Python :: 3
Requires-Python: >=3.7
Requires-Dist: thonny>4.0.0
